pytest_codegen/__init__.py
pytest_codegen/__main__.py
pytest_codegen/main.py
pytest_codegen/templates/filename.template
pytest_codegen/templates/function.template
pytest_codegen/templates/import.template
pytest_codegen/types.py
pytest_codegen-0.0.3.dist-info/entry_points.txt
pytest_codegen-0.0.3.dist-info/WHEEL
pytest_codegen-0.0.3.dist-info/METADATA
pytest_codegen-0.0.3.dist-info/RECORD
