Metadata-Version: 2.1
Name: pytest-codegen
Version: 0.0.3
Summary: Automatically create pytest test signatures
Home-page: https://github.com/jeremyschiemann/pytest-codegen
License: MIT
Author: Jeremy Schiemann
Author-email: jeremy.schiemann@gmail.com
Requires-Python: >=3.8,<4.0
Classifier: Development Status :: 2 - Pre-Alpha
Classifier: License :: OSI Approved :: MIT License
Classifier: Natural Language :: English
Classifier: Programming Language :: Python :: 3
Classifier: Programming Language :: Python :: 3.8
Requires-Dist: jinja2 (>=2.11.2,<3.0.0)
Requires-Dist: redbaron (>=0.9.2,<0.10.0)
Requires-Dist: typer (>=0.3.2,<0.4.0)
Project-URL: Repository, https://github.com/jeremyschiemann/pytest-codegen
